<?xml version="1.0" encoding="UTF-8"?>
<functions>
    <function>
        <name>view</name>
        <uri>view</uri>
    </function>
    <function>
        <name>profile_orders</name>
        <uri>profile_orders</uri>
    </function>
    <function>
        <name>order_detail</name>
        <uri>order_detail</uri>
    </function>
    <function>
        <name>wish_list</name>
        <uri>wish_list</uri>
    </function>
    <function>
        <name>profile_data</name>
        <uri>profile_data</uri>
    </function>
    <function>
        <name>like</name>
        <uri>like</uri>
    </function>
    <function>
        <name>change_pass</name>
        <uri>change_pass</uri>
    </function>
    <function>
        <name>download_pdf</name>
        <uri>download_pdf</uri>
    </function>
    <function>
        <name>show_qr</name>
        <uri>show_qr</uri>
    </function>
</functions>